frameio_kit/__init__.py
frameio_kit/_app.py
frameio_kit/_auth_routes.py
frameio_kit/_client.py
frameio_kit/_context.py
frameio_kit/_encryption.py
frameio_kit/_events.py
frameio_kit/_middleware.py
frameio_kit/_oauth.py
frameio_kit/_responses.py
frameio_kit/_security.py
frameio_kit/py.typed
frameio_kit-0.0.5.dist-info/licenses/LICENSE
frameio_kit-0.0.5.dist-info/WHEEL
frameio_kit-0.0.5.dist-info/METADATA
frameio_kit-0.0.5.dist-info/RECORD
