Metadata-Version: 2.4
Name: frameio-kit
Version: 0.0.5
Summary: A Python framework for building Frame.io apps
Keywords: frameio,frame-io,frame.io,video,collaboration,sdk,api,client,integration,webhook,webhooks,custom-actions,asgi,starlette,async,asyncio,automation,workflow,media,events
License-Expression: MIT
License-File: LICENSE
Classifier: Programming Language :: Python :: 3.13
Classifier: Programming Language :: Python :: Implementation :: CPython
Classifier: License :: OSI Approved :: MIT License
Classifier: Operating System :: OS Independent
Requires-Dist: cryptography>=44.0.0
Requires-Dist: frameio>=0.0.23
Requires-Dist: frameio-experimental>=0.0.3
Requires-Dist: httpx>=0.28.1
Requires-Dist: py-key-value-aio[disk,memory]>=0.1.0
Requires-Dist: pydantic>=2.11.10
Requires-Dist: starlette>=0.48.0
Requires-Python: >=3.13
Project-URL: Changelog, https://github.com/billyshambrook/frameio-kit/releases
Project-URL: Discussions, https://github.com/billyshambrook/frameio-kit/discussions
Project-URL: Documentation, https://billyshambrook.github.io/frameio-kit/
Project-URL: Homepage, https://billyshambrook.github.io/frameio-kit/
Project-URL: Issues, https://github.com/billyshambrook/frameio-kit/issues
Project-URL: Repository, https://github.com/billyshambrook/frameio-kit
